{
"type": "FeatureCollection",
"name": "outlet",
"crs": { "type": "name", "properties": { "name": "urn:ogc:def:crs:OGC:1.3:CRS84" } },
"features": [
{ "type": "Feature", "properties": { "lat": -45.425, "lon": -72.675, "outlets": 6081.0 }, "geometry": { "type": "Point", "coordinates": [ -72.675, -45.425 ] } }
]
}
